zankpy/__init__.py
zankpy/client.py
zankpy/const.py
zankpy-0.0.1.dist-info/METADATA
zankpy-0.0.1.dist-info/WHEEL
zankpy-0.0.1.dist-info/licenses/LICENSE
zankpy-0.0.1.dist-info/RECORD
