Metadata-Version: 2.1
Name: zankpy
Version: 0.0.1
Summary: A client library to interface with the Zank Android TV Remote API
Project-URL: Homepage, https://github.com/zimmra/zankpy
Project-URL: Bug Tracker, https://github.com/zimmra/zankpy/issues
Author-email: Zimmra <payton@zimmerer.io>
License-File: LICENSE
Classifier: License :: OSI Approved :: MIT License
Classifier: Operating System :: OS Independent
Classifier: Programming Language :: Python :: 3
Requires-Python: >=3.7
